plover_palantype_DE/__init__.py
plover_palantype_DE/system.py
plover_palantype_DE/dictionaries/.palantype-DE.json.swp
plover_palantype_DE/dictionaries/palantype-DE-anglicisms.json
plover_palantype_DE/dictionaries/palantype-DE-extra.json
plover_palantype_DE/dictionaries/palantype-DE-min.json
plover_palantype_DE/dictionaries/palantype-DE-numbers.json
plover_palantype_DE/dictionaries/palantype-DE.json
plover_palantype_DE-1.1.4.dist-info/METADATA
plover_palantype_DE-1.1.4.dist-info/WHEEL
plover_palantype_DE-1.1.4.dist-info/entry_points.txt
plover_palantype_DE-1.1.4.dist-info/top_level.txt
plover_palantype_DE-1.1.4.dist-info/zip-safe
plover_palantype_DE-1.1.4.dist-info/RECORD
