Metadata-Version: 2.1
Name: plover-palantype-DE
Version: 1.1.4
Summary: A Palantype-inspired steno system for the German Language
Home-page: https://github.com/rubenmoor/palantype_DE
Author: rubenmoor
Author-email: ruben.moor@gmail.com
License: GNU General Public License v2 or later (GPLv2+)
Keywords: plover plover_plugin
Classifier: Development Status :: 4 - Beta
Classifier: Environment :: Plugins
Classifier: Intended Audience :: End Users/Desktop
Classifier: License :: OSI Approved :: GNU General Public License v2 or later (GPLv2+)
Classifier: Operating System :: OS Independent
Classifier: Programming Language :: Python :: 3
Classifier: Programming Language :: Python :: 3.6
Requires-Dist: plover (>=4.0.0.dev1)
